onebitllms/__init__.py
onebitllms/kernels/__init__.py
onebitllms/kernels/activation_quant.py
onebitllms/kernels/weight_quant.py
onebitllms/layers/__init__.py
onebitllms/layers/bitnet.py
onebitllms/utils/__init__.py
onebitllms/utils/monkey_patching.py
onebitllms/utils/quantization_utils.py
onebitllms-0.0.3.dist-info/licenses/LICENSE
onebitllms-0.0.3.dist-info/METADATA
onebitllms-0.0.3.dist-info/WHEEL
onebitllms-0.0.3.dist-info/top_level.txt
onebitllms-0.0.3.dist-info/RECORD
