Metadata-Version: 2.4
Name: onebitllms
Version: 0.0.3
Summary: Onebit LLMs
Home-page: https://github.com/tiiuae/onebitllms
Author: Technology Innovation Institute - Falcon LLM team
Author-email: younes.belkada@tii.ae
Keywords: deep learning
Classifier: Development Status :: 5 - Production/Stable
Classifier: Intended Audience :: Developers
Classifier: Intended Audience :: Education
Classifier: Intended Audience :: Science/Research
Classifier: Operating System :: OS Independent
Classifier: Programming Language :: Python :: 3
Classifier: Programming Language :: Python :: 3.9
Classifier: Programming Language :: Python :: 3.10
Classifier: Programming Language :: Python :: 3.11
Classifier: Programming Language :: Python :: 3.12
Classifier: Topic :: Scientific/Engineering :: Artificial Intelligence
Requires-Python: >=3.9.0
License-File: LICENSE
Requires-Dist: torch
Requires-Dist: transformers>=4.51.0
Requires-Dist: tqdm
Requires-Dist: accelerate
Requires-Dist: safetensors
Requires-Dist: huggingface_hub
Requires-Dist: setuptools
Provides-Extra: quality
Requires-Dist: black; extra == "quality"
Requires-Dist: ruff~=0.9.2; extra == "quality"
Provides-Extra: dev
Requires-Dist: black; extra == "dev"
Requires-Dist: ruff~=0.9.2; extra == "dev"
Provides-Extra: test
Requires-Dist: black; extra == "test"
Requires-Dist: ruff~=0.9.2; extra == "test"
Requires-Dist: pytest; extra == "test"
Requires-Dist: pytest-cov; extra == "test"
Requires-Dist: pytest-xdist; extra == "test"
Requires-Dist: parameterized; extra == "test"
Dynamic: author
Dynamic: author-email
Dynamic: classifier
Dynamic: description
Dynamic: description-content-type
Dynamic: home-page
Dynamic: keywords
Dynamic: license-file
Dynamic: provides-extra
Dynamic: requires-dist
Dynamic: requires-python
Dynamic: summary
